{"0": "History Analytics & Metrics", "1": "App Routing & Pages", "2": "xP Calculation & Chalk UI", "3": "Domain Model & Agent Governance", "4": "Team Actions & UI Controls", "5": "Formation Validation & ILP Solver", "6": "Expected Points Engine", "7": "Live Stats & Broadsheet", "8": "Brand & Visual Identity", "9": "Core Domain Concepts", "10": "Cache & Error Handling", "11": "App Icons & Static Assets", "12": "Platform & Deployment Config", "13": "History Chart Visualization", "14": "FPL API Proxy", "15": "Predictions API Route", "16": "History API Route", "17": "Bootstrap API Route", "18": "Supabase Client", "19": "ESLint Config", "20": "PostCSS Config", "21": "Next.js Config", "22": "Next.js Type Declarations", "23": "Test Configuration", "24": "Loading State", "25": "Verdict Card Component", "26": "FPL Type Definitions", "27": "Lineup Optimizer", "28": "Admin Module", "29": "FPL API Tests"}